waffledb/__init__.py
waffledb/client.py
waffledb/errors.py
waffledb/types.py
waffledb/utils.py
waffledb-0.2.1.dist-info/LICENSE
waffledb-0.2.1.dist-info/METADATA
waffledb-0.2.1.dist-info/WHEEL
waffledb-0.2.1.dist-info/top_level.txt
waffledb-0.2.1.dist-info/RECORD
