Metadata-Version: 2.1
Name: waffledb
Version: 0.2.1
Summary: Python client for WaffleDB vector database
Home-page: https://github.com/waffledb/waffledb
Author: WaffleDB Team
Author-email: WaffleDB Team <team@waffledb.dev>
License: MIT
Project-URL: Homepage, https://github.com/waffledb/waffledb
Project-URL: Repository, https://github.com/waffledb/waffledb
Project-URL: Documentation, https://waffledb.dev
Keywords: vector-database,similarity-search,embeddings
Classifier: Development Status :: 3 - Alpha
Classifier: Intended Audience :: Developers
Classifier: License :: OSI Approved :: MIT License
Classifier: Programming Language :: Python :: 3
Classifier: Programming Language :: Python :: 3.8
Classifier: Programming Language :: Python :: 3.9
Classifier: Programming Language :: Python :: 3.10
Classifier: Programming Language :: Python :: 3.11
Requires-Python: >=3.8
License-File: LICENSE
Requires-Dist: requests>=2.28.0
Requires-Dist: numpy>=1.20.0
Provides-Extra: dev
Requires-Dist: pytest>=7.0; extra == "dev"
Requires-Dist: black>=23.0; extra == "dev"
Requires-Dist: mypy>=1.0; extra == "dev"
Requires-Dist: pytest-cov>=4.0; extra == "dev"
Requires-Dist: black>=22.0; extra == "dev"
Requires-Dist: isort>=5.10; extra == "dev"
Requires-Dist: mypy>=0.950; extra == "dev"
Requires-Dist: flake8>=4.0; extra == "dev"
